setup.py
spam7.py
spam7.egg-info/PKG-INFO
spam7.egg-info/SOURCES.txt
spam7.egg-info/dependency_links.txt
spam7.egg-info/top_level.txt