Metadata-Version: 2.1
Name: spam7
Version: 1.0.1
Summary: Python module calling
Author: Andy Woz
Classifier: Programming Language :: Python :: 3
Classifier: Operating System :: OS Independent
Requires-Python: >=3.6
